dqn/__init__.py
dqn/agent.py
dqn/environment.py
dqn/game.py
dqn/run_dqn.py
RLDQN-0.0.5.dist-info/LICENSE
RLDQN-0.0.5.dist-info/METADATA
RLDQN-0.0.5.dist-info/WHEEL
RLDQN-0.0.5.dist-info/top_level.txt
RLDQN-0.0.5.dist-info/RECORD
