Metadata-Version: 2.1
Name: RLDQN
Version: 0.0.5
Summary: Asynchronous DQN
Home-page: https://github.com/screenwidth/GameAI/tree/master/RLDQN
Author: maigua
Author-email: 396032050@qq.com
License: MIT
Platform: UNKNOWN
Requires-Dist: numpy (==1.12)
Requires-Dist: tensorflow (==1.1.0)
Requires-Dist: scipy (==0.19.0)
Requires-Dist: Keras (==2.0.4)
Requires-Dist: six (==1.10.0)
Requires-Dist: gym (==0.9.1)
